{
    "Name": "VFR40_5_2_SIST",
    "nMachines": 5,
    "nJobs": 40,
    "Jobs": [
        {
            "Id": 1,
            "SetupTimes": [
                3,
                8,
                6,
                11,
                11
            ],
            "ProcessingTimes": [
                6,
                62,
                27,
                86,
                34
            ],
            "DueDate": 303,
            "TardCosts": 160
        },
        {
            "Id": 2,
            "SetupTimes": [
                16,
                35,
                8,
                11,
                14
            ],
            "ProcessingTimes": [
                32,
                78,
                42,
                66,
                87
            ],
            "DueDate": 376,
            "TardCosts": 90
        },
        {
            "Id": 3,
            "SetupTimes": [
                37,
                11,
                33,
                10,
                4
            ],
            "ProcessingTimes": [
                75,
                46,
                76,
                81,
                9
            ],
            "DueDate": 477,
            "TardCosts": 90
        },
        {
            "Id": 4,
            "SetupTimes": [
                22,
                44,
                15,
                26,
                25
            ],
            "ProcessingTimes": [
                88,
                90,
                43,
                56,
                71
            ],
            "DueDate": 608,
            "TardCosts": 140
        },
        {
            "Id": 5,
            "SetupTimes": [
                15,
                3,
                7,
                42,
                8
            ],
            "ProcessingTimes": [
                33,
                37,
                45,
                98,
                43
            ],
            "DueDate": 332,
            "TardCosts": 130
        },
        {
            "Id": 6,
            "SetupTimes": [
                21,
                2,
                26,
                9,
                23
            ],
            "ProcessingTimes": [
                95,
                11,
                65,
                72,
                63
            ],
            "DueDate": 492,
            "TardCosts": 180
        },
        {
            "Id": 7,
            "SetupTimes": [
                8,
                2,
                4,
                10,
                1
            ],
            "ProcessingTimes": [
                27,
                6,
                10,
                28,
                6
            ],
            "DueDate": 117,
            "TardCosts": 180
        },
        {
            "Id": 8,
            "SetupTimes": [
                15,
                32,
                31,
                0,
                13
            ],
            "ProcessingTimes": [
                98,
                70,
                62,
                1,
                48
            ],
            "DueDate": 331,
            "TardCosts": 130
        },
        {
            "Id": 9,
            "SetupTimes": [
                32,
                38,
                4,
                18,
                14
            ],
            "ProcessingTimes": [
                68,
                83,
                41,
                75,
                52
            ],
            "DueDate": 462,
            "TardCosts": 50
        },
        {
            "Id": 10,
            "SetupTimes": [
                2,
                10,
                11,
                24,
                21
            ],
            "ProcessingTimes": [
                5,
                91,
                99,
                62,
                42
            ],
            "DueDate": 307,
            "TardCosts": 60
        },
        {
            "Id": 11,
            "SetupTimes": [
                7,
                35,
                26,
                20,
                4
            ],
            "ProcessingTimes": [
                23,
                84,
                52,
                94,
                22
            ],
            "DueDate": 310,
            "TardCosts": 170
        },
        {
            "Id": 12,
            "SetupTimes": [
                20,
                20,
                7,
                23,
                13
            ],
            "ProcessingTimes": [
                87,
                81,
                22,
                88,
                32
            ],
            "DueDate": 494,
            "TardCosts": 80
        },
        {
            "Id": 13,
            "SetupTimes": [
                32,
                16,
                26,
                16,
                21
            ],
            "ProcessingTimes": [
                67,
                66,
                94,
                90,
                51
            ],
            "DueDate": 623,
            "TardCosts": 160
        },
        {
            "Id": 14,
            "SetupTimes": [
                5,
                39,
                6,
                11,
                4
            ],
            "ProcessingTimes": [
                19,
                93,
                53,
                25,
                10
            ],
            "DueDate": 222,
            "TardCosts": 100
        },
        {
            "Id": 15,
            "SetupTimes": [
                6,
                5,
                6,
                35,
                9
            ],
            "ProcessingTimes": [
                26,
                15,
                22,
                74,
                42
            ],
            "DueDate": 233,
            "TardCosts": 70
        },
        {
            "Id": 16,
            "SetupTimes": [
                3,
                15,
                7,
                17,
                8
            ],
            "ProcessingTimes": [
                7,
                55,
                31,
                39,
                57
            ],
            "DueDate": 265,
            "TardCosts": 70
        },
        {
            "Id": 17,
            "SetupTimes": [
                34,
                8,
                40,
                9,
                18
            ],
            "ProcessingTimes": [
                73,
                70,
                90,
                53,
                65
            ],
            "DueDate": 413,
            "TardCosts": 50
        },
        {
            "Id": 18,
            "SetupTimes": [
                8,
                1,
                11,
                9,
                18
            ],
            "ProcessingTimes": [
                40,
                13,
                44,
                19,
                66
            ],
            "DueDate": 276,
            "TardCosts": 170
        },
        {
            "Id": 19,
            "SetupTimes": [
                41,
                3,
                7,
                16,
                42
            ],
            "ProcessingTimes": [
                94,
                7,
                30,
                71,
                84
            ],
            "DueDate": 360,
            "TardCosts": 160
        },
        {
            "Id": 20,
            "SetupTimes": [
                15,
                7,
                13,
                2,
                15
            ],
            "ProcessingTimes": [
                55,
                16,
                54,
                17,
                78
            ],
            "DueDate": 285,
            "TardCosts": 190
        },
        {
            "Id": 21,
            "SetupTimes": [
                15,
                4,
                1,
                8,
                41
            ],
            "ProcessingTimes": [
                75,
                41,
                12,
                28,
                88
            ],
            "DueDate": 274,
            "TardCosts": 110
        },
        {
            "Id": 22,
            "SetupTimes": [
                14,
                35,
                23,
                9,
                2
            ],
            "ProcessingTimes": [
                54,
                92,
                92,
                79,
                22
            ],
            "DueDate": 452,
            "TardCosts": 190
        },
        {
            "Id": 23,
            "SetupTimes": [
                14,
                11,
                10,
                16,
                20
            ],
            "ProcessingTimes": [
                89,
                39,
                49,
                40,
                46
            ],
            "DueDate": 320,
            "TardCosts": 200
        },
        {
            "Id": 24,
            "SetupTimes": [
                15,
                23,
                14,
                7,
                12
            ],
            "ProcessingTimes": [
                88,
                74,
                65,
                23,
                74
            ],
            "DueDate": 352,
            "TardCosts": 140
        },
        {
            "Id": 25,
            "SetupTimes": [
                9,
                40,
                23,
                42,
                14
            ],
            "ProcessingTimes": [
                29,
                91,
                73,
                99,
                55
            ],
            "DueDate": 600,
            "TardCosts": 180
        },
        {
            "Id": 26,
            "SetupTimes": [
                16,
                12,
                11,
                6,
                17
            ],
            "ProcessingTimes": [
                43,
                56,
                75,
                19,
                83
            ],
            "DueDate": 333,
            "TardCosts": 110
        },
        {
            "Id": 27,
            "SetupTimes": [
                24,
                2,
                29,
                5,
                13
            ],
            "ProcessingTimes": [
                69,
                23,
                96,
                27,
                59
            ],
            "DueDate": 481,
            "TardCosts": 110
        },
        {
            "Id": 28,
            "SetupTimes": [
                21,
                2,
                0,
                6,
                20
            ],
            "ProcessingTimes": [
                66,
                9,
                1,
                18,
                54
            ],
            "DueDate": 234,
            "TardCosts": 90
        },
        {
            "Id": 29,
            "SetupTimes": [
                22,
                22,
                33,
                19,
                9
            ],
            "ProcessingTimes": [
                71,
                94,
                70,
                67,
                41
            ],
            "DueDate": 416,
            "TardCosts": 160
        },
        {
            "Id": 30,
            "SetupTimes": [
                31,
                6,
                5,
                11,
                28
            ],
            "ProcessingTimes": [
                91,
                38,
                23,
                81,
                72
            ],
            "DueDate": 487,
            "TardCosts": 90
        },
        {
            "Id": 31,
            "SetupTimes": [
                30,
                9,
                25,
                7,
                10
            ],
            "ProcessingTimes": [
                94,
                81,
                64,
                41,
                84
            ],
            "DueDate": 357,
            "TardCosts": 110
        },
        {
            "Id": 32,
            "SetupTimes": [
                27,
                36,
                0,
                21,
                17
            ],
            "ProcessingTimes": [
                93,
                91,
                3,
                54,
                70
            ],
            "DueDate": 564,
            "TardCosts": 100
        },
        {
            "Id": 33,
            "SetupTimes": [
                46,
                38,
                1,
                23,
                31
            ],
            "ProcessingTimes": [
                96,
                91,
                7,
                53,
                68
            ],
            "DueDate": 479,
            "TardCosts": 80
        },
        {
            "Id": 34,
            "SetupTimes": [
                21,
                1,
                1,
                24,
                22
            ],
            "ProcessingTimes": [
                48,
                4,
                7,
                94,
                76
            ],
            "DueDate": 393,
            "TardCosts": 50
        },
        {
            "Id": 35,
            "SetupTimes": [
                23,
                13,
                8,
                6,
                39
            ],
            "ProcessingTimes": [
                60,
                83,
                29,
                26,
                97
            ],
            "DueDate": 343,
            "TardCosts": 180
        },
        {
            "Id": 36,
            "SetupTimes": [
                4,
                9,
                0,
                8,
                2
            ],
            "ProcessingTimes": [
                11,
                25,
                1,
                78,
                12
            ],
            "DueDate": 162,
            "TardCosts": 190
        },
        {
            "Id": 37,
            "SetupTimes": [
                45,
                26,
                2,
                23,
                21
            ],
            "ProcessingTimes": [
                90,
                70,
                10,
                63,
                51
            ],
            "DueDate": 491,
            "TardCosts": 60
        },
        {
            "Id": 38,
            "SetupTimes": [
                16,
                45,
                4,
                11,
                4
            ],
            "ProcessingTimes": [
                43,
                99,
                40,
                36,
                29
            ],
            "DueDate": 326,
            "TardCosts": 60
        },
        {
            "Id": 39,
            "SetupTimes": [
                3,
                0,
                5,
                37,
                20
            ],
            "ProcessingTimes": [
                15,
                6,
                17,
                94,
                48
            ],
            "DueDate": 224,
            "TardCosts": 70
        },
        {
            "Id": 40,
            "SetupTimes": [
                24,
                25,
                9,
                8,
                10
            ],
            "ProcessingTimes": [
                58,
                70,
                92,
                24,
                20
            ],
            "DueDate": 308,
            "TardCosts": 80
        }
    ]
}